trusender/__init__.py
trusender/client.py
trusender_python-0.0.1.dist-info/LICENSE
trusender_python-0.0.1.dist-info/METADATA
trusender_python-0.0.1.dist-info/WHEEL
trusender_python-0.0.1.dist-info/top_level.txt
trusender_python-0.0.1.dist-info/RECORD
