Metadata-Version: 2.1
Name: trusender-python
Version: 0.0.1
Summary: TruSender Python bindings
Home-page: https://github.com/bramu/trusender-python
Author: TruSender
Author-email: bramu.ss@gmail.com
License: UNKNOWN
Platform: UNKNOWN
Classifier: Programming Language :: Python :: 3
Classifier: License :: OSI Approved :: MIT License
Classifier: Operating System :: OS Independent
Requires-Python: >=3.6
